odoo/addons/account_promissory_note_caixabank/README.rst
odoo/addons/account_promissory_note_caixabank/__init__.py
odoo/addons/account_promissory_note_caixabank/__manifest__.py
odoo/addons/account_promissory_note_caixabank/i18n/account_promissory_note_caixabank.pot
odoo/addons/account_promissory_note_caixabank/i18n/ca.po
odoo/addons/account_promissory_note_caixabank/i18n/es.po
odoo/addons/account_promissory_note_caixabank/models/__init__.py
odoo/addons/account_promissory_note_caixabank/models/res_company.py
odoo/addons/account_promissory_note_caixabank/readme/CONFIGURE.md
odoo/addons/account_promissory_note_caixabank/readme/CONTRIBUTORS.md
odoo/addons/account_promissory_note_caixabank/readme/DESCRIPTION.md
odoo/addons/account_promissory_note_caixabank/readme/USAGE.md
odoo/addons/account_promissory_note_caixabank/report/__init__.py
odoo/addons/account_promissory_note_caixabank/report/account_promissory_note_writing_report.xml
odoo/addons/account_promissory_note_caixabank/report/check_print.py
odoo/addons/account_promissory_note_caixabank/static/description/icon.png
odoo/addons/account_promissory_note_caixabank/static/description/index.html
odoo/addons/account_promissory_note_caixabank/views/report_promissory_note.xml
odoo_addon_account_promissory_note_caixabank-18.0.1.0.0.2.dist-info/METADATA
odoo_addon_account_promissory_note_caixabank-18.0.1.0.0.2.dist-info/WHEEL
odoo_addon_account_promissory_note_caixabank-18.0.1.0.0.2.dist-info/top_level.txt
odoo_addon_account_promissory_note_caixabank-18.0.1.0.0.2.dist-info/RECORD
