Metadata-Version: 2.1
Name: odoo-addon-account_promissory_note_caixabank
Version: 18.0.1.0.0.2
Requires-Python: >=3.10
Requires-Dist: odoo-addon-account_check_printing_report_base==18.0.*
Requires-Dist: odoo-addon-account_payment_promissory_note==18.0.*
Requires-Dist: odoo==18.0.*
Summary: =?utf-8?q?Impresi=C3=B3n_de_pagar=C3=A9_CaixaBank_A4?=
Home-page: https://github.com/OCA/l10n-spain
License: AGPL-3
Author: Tecnativa, Odoo Community Association (OCA)
Author-email: support@odoo-community.org
Classifier: Programming Language :: Python
Classifier: Framework :: Odoo
Classifier: Framework :: Odoo :: 18.0
Classifier: License :: OSI Approved :: GNU Affero General Public License v3
